cypher_shell/__init__.py
cypher_shell/__main__.py
cypher_shell/agent.py
cypher_shell/memory.py
cypher_shell/optimizer.py
cypher_shell/query_runner.py
cypher_shell/utils.py
cypher_shell/prompts/__init__.py
cypher_shell/prompts/cypher.py
cypher_shell/prompts/general.py
cypher_shell/prompts/optim.py
cypher_shell-0.5.dist-info/entry_points.txt
cypher_shell-0.5.dist-info/WHEEL
cypher_shell-0.5.dist-info/METADATA
cypher_shell-0.5.dist-info/RECORD
