Metadata-Version: 2.3
Name: cypher-shell
Version: 0.5
Summary: Cypher Shell -- a shell for querying Neo4j with Cypher
Keywords: cypher,neo4j,querying,shell,llm
Author-email: LemurPwned <lemurpwned@gmail.com>
Requires-Python: >3.10
Classifier: Development Status :: 3 - Alpha
Classifier: Environment :: Console
Classifier: Intended Audience :: Developers
Classifier: Natural Language :: English
Classifier: Operating System :: OS Independent
Classifier: Programming Language :: Python
Classifier: Programming Language :: Python :: 3.10
Classifier: Programming Language :: Python :: 3.11
Classifier: Programming Language :: Python :: 3.12
Requires-Dist: pyyaml
Requires-Dist: python-dotenv
Requires-Dist: openai-swarm>=0.1.1
Requires-Dist: typer >= 0.12.5
Requires-Dist: openai >= 1.51.2
Requires-Dist: neo4j >= 5.25.0
Requires-Dist: prompt_toolkit >= 3.0.48
Project-URL: Source, https://github.com/LemurPwned/cypher-shell
